.coveragerc
.coveragrc
.gitignore
.pylintrc
.travis.yml
MANIFEST
README.md
README.rst
run_tests.sh
setup.py
morpheus/__init__.py
morpheus/dict.py
morpheus/exceptions.py
morpheus/operations.py
morpheus/schema.py
morpheus.egg-info/PKG-INFO
morpheus.egg-info/SOURCES.txt
morpheus.egg-info/dependency_links.txt
morpheus.egg-info/top_level.txt
tests/test_dict_cpython.py
tests/test_json_serialization.py
tests/test_module.py
tests/test_morpheusdict.py
tests/test_operations.py
tests/test_package.py
tests/test_performance.py
tests/test_schema.py
tests/test_translation.py
tests/test_usage.py
tests/test_validation.py
tests/test_yaml_serialization.py