Metadata-Version: 1.1
Name: morpheus
Version: 0.0.4
Summary: Dict schema helper for schema-free projects
Home-page: http://github.com/ziadsawalha/morpheus
Author: Ziad Sawalha
Author-email: ziad@sawalha.com
License: Apache 2.0
Keywords: schema NoSQL validation migration
Platform: UNKNOWN
Classifier: Development Status :: 1 - Planning
Classifier: Natural Language :: English
Classifier: Topic :: Utilities
Classifier: Intended Audience :: Developers
Classifier: License :: OSI Approved :: Apache Software License
Classifier: Operating System :: OS Independent
Classifier: Topic :: Database
Classifier: Topic :: Software Development :: Libraries
Classifier: Programming Language :: Python
